smartsheet/__init__.py
smartsheet/attachments.py
smartsheet/cells.py
smartsheet/contacts.py
smartsheet/discussions.py
smartsheet/events.py
smartsheet/exceptions.py
smartsheet/favorites.py
smartsheet/folders.py
smartsheet/groups.py
smartsheet/home.py
smartsheet/images.py
smartsheet/object_value.py
smartsheet/passthrough.py
smartsheet/reports.py
smartsheet/search.py
smartsheet/server.py
smartsheet/session.py
smartsheet/sheets.py
smartsheet/sights.py
smartsheet/smartsheet.py
smartsheet/templates.py
smartsheet/token.py
smartsheet/types.py
smartsheet/users.py
smartsheet/util.py
smartsheet/version.py
smartsheet/webhooks.py
smartsheet/workspaces.py
smartsheet/models/__init__.py
smartsheet/models/access_token.py
smartsheet/models/account.py
smartsheet/models/alternate_email.py
smartsheet/models/attachment.py
smartsheet/models/auto_number_format.py
smartsheet/models/automation_action.py
smartsheet/models/automation_rule.py
smartsheet/models/boolean_object_value.py
smartsheet/models/bulk_item_failure.py
smartsheet/models/bulk_item_result.py
smartsheet/models/cell.py
smartsheet/models/cell_data_item.py
smartsheet/models/cell_history.py
smartsheet/models/cell_link.py
smartsheet/models/cell_link_widget_content.py
smartsheet/models/chart_widget_content.py
smartsheet/models/column.py
smartsheet/models/comment.py
smartsheet/models/contact.py
smartsheet/models/contact_object_value.py
smartsheet/models/container_destination.py
smartsheet/models/copy_or_move_row_destination.py
smartsheet/models/copy_or_move_row_directive.py
smartsheet/models/copy_or_move_row_result.py
smartsheet/models/criteria.py
smartsheet/models/cross_sheet_reference.py
smartsheet/models/currency.py
smartsheet/models/date_object_value.py
smartsheet/models/discussion.py
smartsheet/models/downloaded_file.py
smartsheet/models/duration.py
smartsheet/models/email.py
smartsheet/models/error.py
smartsheet/models/error_result.py
smartsheet/models/event.py
smartsheet/models/event_result.py
smartsheet_python_sdk_py39-2.105.1.10.dist-info/LICENSE.md
smartsheet_python_sdk_py39-2.105.1.10.dist-info/METADATA
smartsheet_python_sdk_py39-2.105.1.10.dist-info/NOTICE
smartsheet_python_sdk_py39-2.105.1.10.dist-info/WHEEL
smartsheet_python_sdk_py39-2.105.1.10.dist-info/top_level.txt
smartsheet_python_sdk_py39-2.105.1.10.dist-info/RECORD
