Metadata-Version: 2.1
Name: smartsheet-python-sdk-py39
Version: 2.105.1.10
Summary: Library that uses Python to connect to Smartsheet services (using API 2.0).
Home-page: http://smartsheet-platform.github.io/api-docs/
Author: Smartsheet
License: Apache-2.0
Keywords: Smartsheet,Collaboration,Project Management,Excel,spreadsheet
Platform: UNKNOWN
Classifier: Development Status :: 5 - Production/Stable
Classifier: Intended Audience :: Developers
Classifier: Natural Language :: English
Classifier: Operating System :: OS Independent
Classifier: License :: OSI Approved :: Apache Software License
Classifier: Programming Language :: Python
Classifier: Programming Language :: Python :: 3.4
Classifier: Programming Language :: Python :: 3.5
Classifier: Programming Language :: Python :: 3.6
Classifier: Programming Language :: Python :: Implementation :: PyPy
Classifier: Programming Language :: Python :: Implementation :: CPython
Classifier: Topic :: Software Development :: Libraries :: Python Modules
Classifier: Topic :: Office/Business :: Financial :: Spreadsheet
License-File: LICENSE.md
License-File: NOTICE
Requires-Dist: requests
Requires-Dist: requests-toolbelt
Requires-Dist: six (>=1.9)
Requires-Dist: certifi
Requires-Dist: python-dateutil
Provides-Extra: develop
Requires-Dist: coverage ; extra == 'develop'
Requires-Dist: coveralls[yaml] ; extra == 'develop'
Requires-Dist: pytest ; extra == 'develop'
Requires-Dist: pytest-instafail ; extra == 'develop'
Provides-Extra: test
Requires-Dist: coverage ; extra == 'test'
Requires-Dist: coveralls ; extra == 'test'
Requires-Dist: pytest ; extra == 'test'
